{
  "items": [
    {
      "sys": { "id": "1" },
      "fields": {
        "title": "Galaxy S10 5G",
        "price": 33000,
        "image": { "fields": { "file": { "url": "./images/product-1.jpeg" } } }
      }
    },
    {
      "sys": { "id": "2" },
      "fields": {
        "title": "Galaxy S10+",
        "price": 29500,
        "image": { "fields": { "file": { "url": "./images/product-2.jpeg" } } }
      }
    },
    {
      "sys": { "id": "3" },
      "fields": {
        "title": "Galaxy S10",
        "price": 26000,
        "image": { "fields": { "file": { "url": "./images/product-3.jpeg" } } }
      }
    },
    {
      "sys": { "id": "4" },
      "fields": {
        "title": "Galaxy S10e",
        "price": 23000,
        "image": { "fields": { "file": { "url": "./images/product-4.jpeg" } } }
      }
    },
    {
      "sys": { "id": "5" },
      "fields": {
        "title": "Galaxy A2 Core",
        "price": 25000,
        "image": { "fields": { "file": { "url": "./images/product-5.jpeg" } } }
      }
    },
    {
      "sys": { "id": "6" },
      "fields": {
        "title": "Galaxy M30",
        "price": 19000,
        "image": { "fields": { "file": { "url": "./images/product-6.jpeg" } } }
      }
    },
    {
      "sys": { "id": "7" },
      "fields": {
        "title": "Galaxy M20",
        "price": 19500,
        "image": { "fields": { "file": { "url": "./images/product-7.jpeg" } } }
      }
    },
    {
      "sys": { "id": "8" },
      "fields": {
        "title": "Galaxy M10",
        "price": 16000,
        "image": { "fields": { "file": { "url": "./images/product-8.jpeg" } } }
      }
    },
    {
      "sys": {
        "id": "9"
      },
      "fields": {
        "title": "Galaxy A80",
        "price": 14000,
        "image": {
          "fields": {
            "file": {
              "url": "./images/product-9.jpeg"
            }
          }
        }
      }
    },
    {
      "sys": {
        "id": "10"
      },
      "fields": {
        "title": "Galaxy A70",
        "price": 13500,
        "image": {
          "fields": {
            "file": {
              "url": "./images/product-10.jpeg"
            }
          }
        }
      }
    },
    {
      "sys": {
        "id": "11"
      },
      "fields": {
        "title": "Galaxy A60",
        "price": 10500,
        "image": {
          "fields": {
            "file": {
              "url": "./images/product-11.jpeg"
            }
          }
        }
      }
    },
    {
      "sys": {
        "id": "12"
      },
      "fields": {
        "title": "Galaxy A30",
        "price": 9000,
        "image": {
          "fields": {
            "file": {
              "url": "./images/product-12.jpeg"
            }
          }
        }
      }
    }
  ]
}
